decologger/DecoLogger.py
decologger/__init__.py
DecoLogger-0.0.5.dist-info/METADATA
DecoLogger-0.0.5.dist-info/WHEEL
DecoLogger-0.0.5.dist-info/top_level.txt
DecoLogger-0.0.5.dist-info/RECORD
